nerdron/__init__.py
nerdron/activation.py
nerdron/layer.py
nerdron/network.py
nerdron-0.3.2.dist-info/METADATA
nerdron-0.3.2.dist-info/WHEEL
nerdron-0.3.2.dist-info/top_level.txt
nerdron-0.3.2.dist-info/RECORD
