Metadata-Version: 2.1
Name: nerdron
Version: 0.3.2
Summary: A simple and flexible neural network package
Home-page: https://github.com/MuhammadRamzy/nerdron
Author: Muhammad Ramzy
Author-email: mhdramzy777@gmail.com
Classifier: Programming Language :: Python :: 3
Classifier: License :: OSI Approved :: MIT License
Classifier: Operating System :: OS Independent
Requires-Python: >=3.6
Requires-Dist: numpy>=1.19.2
